LICENSE
MANIFEST.in
README.rst
setup.py
address/__init__.py
address/admin.py
address/apps.py
address/forms.py
address/models.py
address/tests.py
address/views.py
address/migrations/0001_initial.py
address/migrations/__init__.py
django_simple_address.egg-info/PKG-INFO
django_simple_address.egg-info/SOURCES.txt
django_simple_address.egg-info/dependency_links.txt
django_simple_address.egg-info/top_level.txt